setup.py
conj/__init__.py
conj.egg-info/PKG-INFO
conj.egg-info/SOURCES.txt
conj.egg-info/dependency_links.txt
conj.egg-info/not-zip-safe
conj.egg-info/requires.txt
conj.egg-info/top_level.txt