Metadata-Version: 1.0
Name: conj
Version: 1.3
Summary: Python conjugation module for Turkish
Home-page: https://github.com/halilkaya/conj
Author: Halil Kaya
Author-email: halil@halilkaya.net
License: GPLv3
Platform: UNKNOWN
